helx/__init__.py
helx/_version.py
helx/agents/__init__.py
helx/agents/agent.py
helx/agents/ddqn.py
helx/agents/dqn.py
helx/agents/dueling_dqn.py
helx/agents/random.py
helx/agents/sac.py
helx/agents/sacd.py
helx/base/__init__.py
helx/base/config.py
helx/base/image.py
helx/base/losses.py
helx/base/mdp.py
helx/base/memory.py
helx/base/modules.py
helx/base/preprocess.py
helx/base/spaces.py
helx/envs/__init__.py
helx/envs/brax.py
helx/envs/bsuite.py
helx/envs/dm_env.py
helx/envs/environment.py
helx/envs/gym.py
helx/envs/gymnasium.py
helx/envs/gymnax.py
helx/envs/interop.py
helx/envs/navix.py
helx/experiment/__init__.py
helx/experiment/logging.py
helx/experiment/running.py
HELX-1.1.5.dist-info/AUTHORS
HELX-1.1.5.dist-info/LICENSE
HELX-1.1.5.dist-info/METADATA
HELX-1.1.5.dist-info/NOTICE
HELX-1.1.5.dist-info/WHEEL
HELX-1.1.5.dist-info/top_level.txt
HELX-1.1.5.dist-info/RECORD
